rtd/__init__.py
rtd/main.py
rtd_cli-0.1.0.dist-info/METADATA
rtd_cli-0.1.0.dist-info/WHEEL
rtd_cli-0.1.0.dist-info/entry_points.txt
rtd_cli-0.1.0.dist-info/top_level.txt
rtd_cli-0.1.0.dist-info/RECORD
