Metadata-Version: 2.4
Name: rtd-cli
Version: 0.1.0
Summary: Simple CLI wrapper for the Readthedocs REST API
Author-email: Ryan Williams <ryan@runsascoded.com>
License: MIT
Project-URL: Repository, https://github.com/runsascoded/rtd.py
Project-URL: Issues, https://github.com/runsascoded/rtd.py/issues
Keywords: readthedocs,rtd,cli,docs
Classifier: Development Status :: 3 - Alpha
Classifier: Intended Audience :: Developers
Classifier: License :: OSI Approved :: MIT License
Classifier: Programming Language :: Python :: 3
Classifier: Programming Language :: Python :: 3.10
Classifier: Programming Language :: Python :: 3.11
Classifier: Programming Language :: Python :: 3.12
Classifier: Programming Language :: Python :: 3.13
Requires-Python: >=3.10
Requires-Dist: click
Requires-Dist: requests
